{
  "updated_at": "2026-07-24T03:41:41.825Z",
  "components": [
    {
      "id": "api-staging",
      "name": "API",
      "environment": "staging",
      "status": "down",
      "response_ms": 110,
      "last_checked": "2026-07-24T03:41:40.569Z"
    },
    {
      "id": "api-prod",
      "name": "API",
      "environment": "prod",
      "status": "down",
      "response_ms": 90,
      "last_checked": "2026-07-24T03:41:40.766Z"
    },
    {
      "id": "storefront-staging",
      "name": "Storefront",
      "environment": "staging",
      "status": "down",
      "response_ms": 96,
      "last_checked": "2026-07-24T03:41:40.963Z"
    },
    {
      "id": "storefront-prod",
      "name": "Storefront",
      "environment": "prod",
      "status": "down",
      "response_ms": 168,
      "last_checked": "2026-07-24T03:41:41.231Z"
    },
    {
      "id": "backoffice-staging",
      "name": "Backoffice",
      "environment": "staging",
      "status": "down",
      "response_ms": 116,
      "last_checked": "2026-07-24T03:41:41.447Z"
    },
    {
      "id": "backoffice-prod",
      "name": "Backoffice",
      "environment": "prod",
      "status": "down",
      "response_ms": 175,
      "last_checked": "2026-07-24T03:41:41.723Z"
    },
    {
      "id": "suppliers",
      "name": "Suppliers",
      "environment": "—",
      "status": "unknown",
      "response_ms": null,
      "last_checked": null
    }
  ]
}
