{
  "updated_at": "2026-05-13T22:39:06.254Z",
  "components": [
    {
      "id": "api-staging",
      "name": "API",
      "environment": "staging",
      "status": "down",
      "response_ms": 171,
      "last_checked": "2026-05-13T22:39:04.938Z"
    },
    {
      "id": "api-prod",
      "name": "API",
      "environment": "prod",
      "status": "down",
      "response_ms": 112,
      "last_checked": "2026-05-13T22:39:05.342Z"
    },
    {
      "id": "storefront-staging",
      "name": "Storefront",
      "environment": "staging",
      "status": "down",
      "response_ms": 123,
      "last_checked": "2026-05-13T22:39:05.566Z"
    },
    {
      "id": "storefront-prod",
      "name": "Storefront",
      "environment": "prod",
      "status": "down",
      "response_ms": 55,
      "last_checked": "2026-05-13T22:39:05.721Z"
    },
    {
      "id": "backoffice-staging",
      "name": "Backoffice",
      "environment": "staging",
      "status": "down",
      "response_ms": 122,
      "last_checked": "2026-05-13T22:39:05.943Z"
    },
    {
      "id": "backoffice-prod",
      "name": "Backoffice",
      "environment": "prod",
      "status": "down",
      "response_ms": 108,
      "last_checked": "2026-05-13T22:39:06.152Z"
    },
    {
      "id": "suppliers",
      "name": "Suppliers",
      "environment": "—",
      "status": "unknown",
      "response_ms": null,
      "last_checked": null
    }
  ]
}
